{"lastUsed":1597302991451,"path":"D:\/spring-workspace","projectCount":1,"recentFiles":[{"path":"\/Lecture-Spring\/src\/main\/java\/di\/xml\/n01","parentWorkspace":"D:\/spring-workspace","name":"HankookTire.java","lastModified":1597294875172,"locationURI":"file:\/D:\/spring-workspace\/Lecture-Spring\/src\/main\/java\/di\/xml\/n01\/HankookTire.java"},{"path":"\/Lecture-Spring\/src\/main\/java\/basic","parentWorkspace":"D:\/spring-workspace","name":"HelloSingle.java","lastModified":1597285261489,"locationURI":"file:\/D:\/spring-workspace\/Lecture-Spring\/src\/main\/java\/basic\/HelloSingle.java"},{"path":"\/Lecture-Spring\/src\/main\/java\/di\/xml\/n02","parentWorkspace":"D:\/spring-workspace","name":"DriverMain.java","lastModified":1597298345290,"locationURI":"file:\/D:\/spring-workspace\/Lecture-Spring\/src\/main\/java\/di\/xml\/n02\/DriverMain.java"},{"path":"\/Lecture-Spring\/src\/main\/java\/di\/basic","parentWorkspace":"D:\/spring-workspace","name":"DriverMain.java","lastModified":1597293886130,"locationURI":"file:\/D:\/spring-workspace\/Lecture-Spring\/src\/main\/java\/di\/basic\/DriverMain.java"},{"path":"\/Lecture-Spring\/src\/main\/resources","parentWorkspace":"D:\/spring-workspace","name":"beanContainer.xml","lastModified":1597285190959,"locationURI":"file:\/D:\/spring-workspace\/Lecture-Spring\/src\/main\/resources\/beanContainer.xml"},{"path":"\/Lecture-Spring\/src\/main\/java\/di\/xml\/n01","parentWorkspace":"D:\/spring-workspace","name":"Car.java","lastModified":1597294875172,"locationURI":"file:\/D:\/spring-workspace\/Lecture-Spring\/src\/main\/java\/di\/xml\/n01\/Car.java"},{"path":"\/Lecture-Spring\/src\/main\/java\/di\/anno\/n01","parentWorkspace":"D:\/spring-workspace","name":"DriverMain.java","lastModified":1597303016632,"locationURI":"file:\/D:\/spring-workspace\/Lecture-Spring\/src\/main\/java\/di\/anno\/n01\/DriverMain.java"},{"path":"\/Lecture-Spring\/src\/main\/resources","parentWorkspace":"D:\/spring-workspace","name":"di-xml01.xml","lastModified":1597298372659,"locationURI":"file:\/D:\/spring-workspace\/Lecture-Spring\/src\/main\/resources\/di-xml01.xml"},{"path":"\/Lecture-Spring\/src\/main\/java\/di\/basic","parentWorkspace":"D:\/spring-workspace","name":"HankookTire.java","lastModified":1597285657815,"locationURI":"file:\/D:\/spring-workspace\/Lecture-Spring\/src\/main\/java\/di\/basic\/HankookTire.java"},{"path":"\/Lecture-Spring\/src\/main\/resources","parentWorkspace":"D:\/spring-workspace","name":"di-anno01.xml","lastModified":1597303000321,"locationURI":"file:\/D:\/spring-workspace\/Lecture-Spring\/src\/main\/resources\/di-anno01.xml"},{"path":"\/Lecture-Spring\/src\/main\/java\/basic","parentWorkspace":"D:\/spring-workspace","name":"HelloMain.java","lastModified":1597301465331,"locationURI":"file:\/D:\/spring-workspace\/Lecture-Spring\/src\/main\/java\/basic\/HelloMain.java"},{"path":"\/Lecture-Spring\/src\/main\/java\/di\/basic","parentWorkspace":"D:\/spring-workspace","name":"Car.java","lastModified":1597296717448,"locationURI":"file:\/D:\/spring-workspace\/Lecture-Spring\/src\/main\/java\/di\/basic\/Car.java"},{"path":"\/Lecture-Spring\/src\/main\/java\/di\/basic","parentWorkspace":"D:\/spring-workspace","name":"Tire.java","lastModified":1597285621671,"locationURI":"file:\/D:\/spring-workspace\/Lecture-Spring\/src\/main\/java\/di\/basic\/Tire.java"},{"path":"\/Lecture-Spring\/src\/main\/java\/di\/xml\/n01","parentWorkspace":"D:\/spring-workspace","name":"DriverMain.java","lastModified":1597301465331,"locationURI":"file:\/D:\/spring-workspace\/Lecture-Spring\/src\/main\/java\/di\/xml\/n01\/DriverMain.java"},{"path":"\/Lecture-Spring","parentWorkspace":"D:\/spring-workspace","name":"pom.xml","lastModified":1597280404314,"locationURI":"file:\/D:\/spring-workspace\/Lecture-Spring\/pom.xml"},{"path":"\/Lecture-Spring\/src\/main\/java\/di\/basic","parentWorkspace":"D:\/spring-workspace","name":"KumhoTire.java","lastModified":1597285992021,"locationURI":"file:\/D:\/spring-workspace\/Lecture-Spring\/src\/main\/java\/di\/basic\/KumhoTire.java"},{"path":"\/Lecture-Spring\/src\/main\/java\/basic","parentWorkspace":"D:\/spring-workspace","name":"Hello.java","lastModified":1597284870138,"locationURI":"file:\/D:\/spring-workspace\/Lecture-Spring\/src\/main\/java\/basic\/Hello.java"},{"path":"\/Lecture-Spring\/src\/main\/java\/di\/xml\/n02","parentWorkspace":"D:\/spring-workspace","name":"Car.java","lastModified":1597298482120,"locationURI":"file:\/D:\/spring-workspace\/Lecture-Spring\/src\/main\/java\/di\/xml\/n02\/Car.java"},{"path":"\/Lecture-Spring\/src\/main\/java\/di\/basic","parentWorkspace":"D:\/spring-workspace","name":"객체관계도.cld","lastModified":1597286270330,"locationURI":"file:\/D:\/spring-workspace\/Lecture-Spring\/src\/main\/java\/di\/basic\/객체관계도.cld"},{"path":"\/Lecture-Spring\/src\/main\/java\/di\/anno\/n01","parentWorkspace":"D:\/spring-workspace","name":"Car.java","lastModified":1597303016632,"locationURI":"file:\/D:\/spring-workspace\/Lecture-Spring\/src\/main\/java\/di\/anno\/n01\/Car.java"},{"path":"\/Lecture-Spring\/src\/main\/java\/di\/basic","parentWorkspace":"D:\/spring-workspace","name":"자동차구매.sqd","lastModified":1597293274493,"locationURI":"file:\/D:\/spring-workspace\/Lecture-Spring\/src\/main\/java\/di\/basic\/자동차구매.sqd"},{"path":"\/Lecture-Spring\/src\/main\/resources","parentWorkspace":"D:\/spring-workspace","name":"di-xml02.xml","lastModified":1597298464658,"locationURI":"file:\/D:\/spring-workspace\/Lecture-Spring\/src\/main\/resources\/di-xml02.xml"}]}